aoe/__init__.py
aoe/shell/__init__.py
aoe/shell/usage.py
aoe/src/temp.txt
package_name/__init__.py
package_name/shell/__init__.py
package_name/shell/usage.py
package_name/src/temp.txt
aoe-0.0.1.dist-info/LICENSE
aoe-0.0.1.dist-info/METADATA
aoe-0.0.1.dist-info/WHEEL
aoe-0.0.1.dist-info/entry_points.txt
aoe-0.0.1.dist-info/top_level.txt
aoe-0.0.1.dist-info/zip-safe
aoe-0.0.1.dist-info/RECORD
